anibridge_mal_provider/__init__.py
anibridge_mal_provider/client.py
anibridge_mal_provider/list.py
anibridge_mal_provider/models.py
anibridge_mal_provider-0.1.0.dist-info/WHEEL
anibridge_mal_provider-0.1.0.dist-info/METADATA
anibridge_mal_provider-0.1.0.dist-info/RECORD
