Metadata-Version: 2.3
Name: anibridge-mal-provider
Version: 0.1.0
Summary: MAL provider for the AniBridge project.
Author: Elias Benbourenane
Author-email: Elias Benbourenane <eliasbenbourenane@gmail.com>
Classifier: Programming Language :: Python :: 3
Classifier: Programming Language :: Python :: 3.14
Classifier: License :: OSI Approved :: MIT License
Classifier: Operating System :: OS Independent
Requires-Dist: aiohttp>=3.13.3
Requires-Dist: anibridge-library-base>=0.1.1
Requires-Dist: anibridge-list-base>=0.1.1
Requires-Dist: limiter>=0.5.0
Requires-Dist: pydantic>=2.12.5
Maintainer: Elias Benbourenane
Maintainer-email: Elias Benbourenane <eliasbenbourenane@gmail.com>
Requires-Python: >=3.14
